AUTHORS
LICENSE
MANIFEST.in
VERSION
requirements.txt
setup.py
django_gollum.egg-info/PKG-INFO
django_gollum.egg-info/SOURCES.txt
django_gollum.egg-info/dependency_links.txt
django_gollum.egg-info/requires.txt
django_gollum.egg-info/top_level.txt
docs/Makefile
docs/conf.py
docs/css.rst
docs/html.rst
docs/index.rst
docs/settings.rst
docs/usage.rst
docs/_build/doctrees/css.doctree
docs/_build/doctrees/environment.pickle
docs/_build/doctrees/html.doctree
docs/_build/doctrees/index.doctree
docs/_build/doctrees/settings.doctree
docs/_build/doctrees/templates.doctree
docs/_build/doctrees/usage.doctree
docs/_build/html/.buildinfo
docs/_build/html/css.html
docs/_build/html/genindex.html
docs/_build/html/html.html
docs/_build/html/index.html
docs/_build/html/objects.inv
docs/_build/html/search.html
docs/_build/html/searchindex.js
docs/_build/html/settings.html
docs/_build/html/templates.html
docs/_build/html/usage.html
docs/_build/html/_sources/css.txt
docs/_build/html/_sources/html.txt
docs/_build/html/_sources/index.txt
docs/_build/html/_sources/settings.txt
docs/_build/html/_sources/templates.txt
docs/_build/html/_sources/usage.txt
docs/_build/html/_static/ajax-loader.gif
docs/_build/html/_static/basic.css
docs/_build/html/_static/comment-bright.png
docs/_build/html/_static/comment-close.png
docs/_build/html/_static/comment.png
docs/_build/html/_static/default.css
docs/_build/html/_static/doctools.js
docs/_build/html/_static/down-pressed.png
docs/_build/html/_static/down.png
docs/_build/html/_static/file.png
docs/_build/html/_static/jquery.js
docs/_build/html/_static/minus.png
docs/_build/html/_static/plus.png
docs/_build/html/_static/pygments.css
docs/_build/html/_static/searchtools.js
docs/_build/html/_static/sidebar.js
docs/_build/html/_static/underscore.js
docs/_build/html/_static/up-pressed.png
docs/_build/html/_static/up.png
docs/_build/html/_static/websupport.js
gollum/VERSION
gollum/__init__.py
gollum/fields.py
gollum/forms.py
gollum/mixins.py
gollum/utils.py