Metadata-Version: 1.1
Name: django-gollum
Version: 1.0.0
Summary: Better Django Form HTML/CSS customization. For Python 2 or Python 3.
Home-page: https://github.com/lukesneeringer/django-gollum
Author: Luke Sneeringer
Author-email: luke@sneeringer.com
License: New BSD
Platform: UNKNOWN
Classifier: Development Status :: 5 - Production/Stable
Classifier: Environment :: Web Environment
Classifier: Framework :: Django
Classifier: Intended Audience :: Developers
Classifier: License :: OSI Approved :: BSD License
Classifier: Operating System :: OS Independent
Classifier: Programming Language :: Python
Classifier: Programming Language :: Python :: 2.7
Classifier: Programming Language :: Python :: 3.3
Classifier: Topic :: Database
Classifier: Topic :: Software Development
Provides: gollum
